{
  "todos": [
    {
      "id": 1,
      "title": "Title",
      "completed": true,
      "description": "Who really killed Lilly Kane?",
      "tags": [
        {
          "id": 1,
          "tag": "angular"
        },
        {
          "id": 2,
          "tag": "react"
        },
        {
          "id": 3,
          "tag": "typescript"
        }
      ]
    },
    {
      "id": 2,
      "title": "Title",
      "description": "What’s gotten in to Duncan?",
      "completed": false,
      "tags": [
        {
          "id": 1,
          "tag": "angular"
        },
        {
          "id": 2,
          "tag": "react"
        }
      ]
    },
    {
      "id": 3,
      "description": "What happened the night of Shelly Pomroy's party?",
      "completed": false,
      "title": "Title"
    },
    {
      "id": 4,
      "title": "Title",
      "description": "Where did Veronica's mom go and why did she leave?",
      "completed": false,
      "tags": [
        {
          "id": 3,
          "tag": "typescript"
        }
      ]
    },
    {
      "id": 5,
      "title": "Title",
      "description": "Who stole the money at Logan’s poker game?",
      "completed": false
    },
    {
      "id": 6,
      "title": "Title",
      "description": "Who was Jackie with at Java the Hut?",
      "completed": false
    },
    {
      "id": 7,
      "title": "Title",
      "description": "Can Jackie get Wallace to help find out who hit her father's car?",
      "completed": false
    },
    {
      "id": 8,
      "title": "Title",
      "description": "How did the bus crash?",
      "completed": false
    },
    {
      "id": 9,
      "title": "test",
      "done": false
    },
    {
      "id": 10,
      "title": "test",
      "done": false
    }
  ],
  "tags": [
    {
      "id": 1,
      "tag": "react"
    },
    {
      "id": 2,
      "tag": "angular"
    },
    {
      "id": 3,
      "tag": "typescript"
    },
    {
      "id": 4,
      "tag": "rxjs"
    },
    {
      "id": 5,
      "tag": "functional programming"
    }
  ]
}